[
  {
    "id": "nD3U-G5fFyJmzVnhJoCOV",
    "name": "money",
    "type": "10001",
    "attributes": {
      "gridProps": [
        {
          "componentId": "uxoney5wS_m0Z95g5CW_t",
          "componentType": "10001",
          "id": "uxoney5wS_m0Z95g5CW_t",
          "position": {
            "i": "uxoney5wS_m0Z95g5CW_t",
            "x": null,
            "y": null,
            "w": null,
            "h": null
          },
          "layoutProperties": { "lg": 12, "md": 12, "sm": 12, "xs": 12 }
        }
      ]
    },
    "layout": [
      {
        "id": "uxoney5wS_m0Z95g5CW_t",
        "status": "ACTIVE",
        "_id": "610134a1d1f5e860b1e8c751",
        "name": "Grid layout",
        "icon": "FaGripHorizontal",
        "attributes": {
          "gridProps": [],
          "label": "Header",
          "layoutProperties": {
            "gridLayout": {
              "//": "Use this class to style grid layout component.",
              "padding": "5px",
              "spacing": 0,
              "text-align": "center"
            },
            "mainContainer": "gridLayout"
          },
          "layoutProps": {
            "direction": "row",
            "justifyContent": "flex-start",
            "alignItems": "flex-start"
          },
          "direction": "row",
          "name": "Grid layout"
        },
        "group": "Layout",
        "type": "sidebarItem",
        "updatedAt": "23-Sep-2021",
        "Documentation": "<div>\n<table style=\"border-collapse: collapse; width: 99.8899%;\" border=\"1\">\n<tbody>\n<tr>\n<td style=\"width: 48.4024%;\">1</td>\n<td style=\"width: 48.4024%;\">&nbsp;</td>\n</tr>\n<tr>\n<td style=\"width: 48.4024%;\">2</td>\n<td style=\"width: 48.4024%;\">&nbsp;</td>\n</tr>\n<tr>\n<td style=\"width: 48.4024%;\">43</td>\n<td style=\"width: 48.4024%;\">&nbsp;</td>\n</tr>\n<tr>\n<td style=\"width: 48.4024%;\">6</td>\n<td style=\"width: 48.4024%;\">&nbsp;</td>\n</tr>\n<tr>\n<td style=\"width: 48.4024%;\">7</td>\n<td style=\"width: 48.4024%;\">&nbsp;</td>\n</tr>\n</tbody>\n</table>\nWrite your Docu7mentationtestsdfasd</div>",
        "createdAt": "24-Aug-2021",
        "events": [],
        "order": 1,
        "version": "1.0.0",
        "isLatest": true,
        "projectType": "web",
        "allowedContainers": ["10001", "20030", "noLayout", "20010", "widget"],
        "component": { "content": "Grid layout", "type": "10001" },
        "path": "0",
        "gridProps": [
          {
            "type": "column",
            "id": "odMZDV6niP6lvO4F1mug3",
            "gridProps": [
              {
                "type": "10001",
                "name": "Money",
                "id": "2JxPGvYnRHsvswl5lmItd",
                "gridProps": [
                  {
                    "type": "column",
                    "id": "X8RdDSZn4cGHAa-HTQQd7",
                    "gridProps": [
                      {
                        "id": "kZHz9AuGXUZipMd4gJ5Xe",
                        "status": "ACTIVE",
                        "name": "Label",
                        "attributes": {
                          "variant": "body1",
                          "name": "Label",
                          "mandatory": false,
                          "layoutProperties": {
                            "label": {
                              "//": "Use this class to style label component.",
                              "text-align": "center",
                              "font-weigth": "bold"
                            },
                            "mainContainer": "label",
                            "xl": 12,
                            "lg": 12,
                            "md": 12,
                            "sm": 12,
                            "xs": 12
                          },
                          "label": "**********"
                        },
                        "icon": "FaFont",
                        "group": "Form",
                        "type": "20002",
                        "updatedAt": "23-Aug-2021",
                        "createdAt": "23-Aug-2021",
                        "order": 15,
                        "version": "1.0.0",
                        "isLatest": true,
                        "projectType": "web",
                        "component": { "content": "Label", "type": "20002" },
                        "events": [],
                        "path": "0-0-0-0-0"
                      }
                    ],
                    "layoutProperties": {
                      "xl": 12,
                      "lg": 12,
                      "md": 12,
                      "sm": 12,
                      "xs": 12
                    }
                  }
                ],
                "allowedContainers": [
                  "10001",
                  "20030",
                  "noLayout",
                  "20010",
                  "widget"
                ],
                "attributes": {
                  "gridProps": [],
                  "label": "Header",
                  "layoutProperties": {
                    "gridLayout": {
                      "//": "Use this class to style grid layout component.",
                      "padding": "5px",
                      "spacing": 0,
                      "width": "10%",
                      "height": "80px",
                      "text-align": "center"
                    },
                    "mainContainer": "gridLayout"
                  },
                  "layoutProps": {
                    "direction": "row",
                    "justifyContent": "flex-start",
                    "alignItems": "flex-start"
                  },
                  "direction": "row",
                  "name": "Money",
                  "isSwappable": true
                },
                "events": [],
                "component": { "type": "10001", "content": "Grid layout" },
                "path": "0-0-0",
                "dimensions": {
                  "rows": 1,
                  "columns": 1,
                  "colSize0xs": 12,
                  "colSize0sm": 12,
                  "colSize0md": 12,
                  "colSize0lg": 12,
                  "colSize0xl": 12
                },
                "readOnly": true
              }
            ],
            "layoutProperties": {
              "xl": 12,
              "lg": 12,
              "md": 12,
              "sm": 12,
              "xs": 12
            }
          }
        ],
        "layoutProperties": { "lg": 12, "md": 12, "sm": 12, "xs": 12 }
      }
    ],
    "events": [],
    "subType": "widget",
    "screenId": "nD3U-G5fFyJmzVnhJoCOV",
    "projectId": "655616226a9c9c0f149fbf8e",
    "version": "1.0.0",
    "gitBranchName": "master",
    "_id": "nD3U-G5fFyJmzVnhJoCOV",
    "createdBy": "basitahmed1199",
    "updatedAt": "11/23/2023",
    "createdAt": "11/23/2023",
    "updatedTimestamp": "0000-00-00T00:00:00+00:00"
  },
  {
    "id": "uxoney5wS_m0Z95g5CW_t",
    "name": "Grid layout",
    "type": "10001",
    "attributes": {
      "gridProps": [
        {
          "componentId": "2JxPGvYnRHsvswl5lmItd",
          "componentType": "10001",
          "id": "2JxPGvYnRHsvswl5lmItd",
          "position": {
            "i": "2JxPGvYnRHsvswl5lmItd",
            "x": null,
            "y": null,
            "w": null,
            "h": null
          },
          "layoutProperties": {
            "xl": 12,
            "lg": 12,
            "md": 12,
            "sm": 12,
            "xs": 12
          }
        }
      ],
      "label": "Header",
      "layoutProperties": {
        "gridLayout": {
          "//": "Use this class to style grid layout component.",
          "padding": "5px",
          "spacing": 0,
          "text-align": "center"
        },
        "mainContainer": "gridLayout"
      },
      "layoutProps": {
        "direction": "row",
        "justifyContent": "flex-start",
        "alignItems": "flex-start"
      },
      "direction": "row",
      "name": "Grid layout"
    },
    "layout": null,
    "events": [],
    "subType": "component",
    "screenId": "nD3U-G5fFyJmzVnhJoCOV",
    "projectId": "655616226a9c9c0f149fbf8e",
    "version": "1.0.0",
    "gitBranchName": "master",
    "updatedTimestamp": "0000-00-00T00:00:00+00:00"
  },
  {
    "id": "2JxPGvYnRHsvswl5lmItd",
    "name": "Money",
    "type": "10001",
    "attributes": {
      "gridProps": [
        {
          "layoutProperties": {
            "xl": 12,
            "lg": 12,
            "md": 12,
            "sm": 12,
            "xs": 12
          },
          "componentId": "kZHz9AuGXUZipMd4gJ5Xe",
          "componentType": "20002",
          "order": 1
        }
      ],
      "label": "Header",
      "layoutProperties": {
        "gridLayout": {
          "//": "Use this class to style grid layout component.",
          "padding": "5px",
          "spacing": 0,
          "width": "10%",
          "height": "80px",
          "text-align": "center"
        },
        "mainContainer": "gridLayout"
      },
      "layoutProps": {
        "direction": "row",
        "justifyContent": "flex-start",
        "alignItems": "flex-start"
      },
      "direction": "row",
      "name": "Money",
      "isSwappable": true
    },
    "layout": null,
    "events": [],
    "subType": "component",
    "screenId": "nD3U-G5fFyJmzVnhJoCOV",
    "projectId": "655616226a9c9c0f149fbf8e",
    "version": "1.0.0",
    "gitBranchName": "master",
    "updatedTimestamp": "0000-00-00T00:00:00+00:00"
  },
  {
    "id": "kZHz9AuGXUZipMd4gJ5Xe",
    "status": "ACTIVE",
    "name": "Label",
    "attributes": {
      "variant": "body1",
      "name": "Label",
      "mandatory": false,
      "layoutProperties": {
        "label": {
          "//": "Use this class to style label component.",
          "text-align": "center",
          "font-weigth": "bold"
        },
        "mainContainer": "label",
        "xl": 12,
        "lg": 12,
        "md": 12,
        "sm": 12,
        "xs": 12
      },
      "label": "**********"
    },
    "icon": "FaFont",
    "group": "Form",
    "type": "20002",
    "updatedAt": "23-Aug-2021",
    "createdAt": "23-Aug-2021",
    "order": 15,
    "version": "1.0.0",
    "isLatest": true,
    "projectType": "web",
    "component": { "content": "Label", "type": "20002" },
    "events": [],
    "path": "0-0-0-0-0",
    "screenId": "nD3U-G5fFyJmzVnhJoCOV",
    "subType": "component",
    "projectId": "655616226a9c9c0f149fbf8e",
    "gitBranchName": "master",
    "updatedTimestamp": "0000-00-00T00:00:00+00:00"
  }
]
